qh3-1.5.6.dist-info/METADATA
qh3-1.5.6.dist-info/WHEEL
qh3-1.5.6.dist-info/licenses/LICENSE
qh3/__init__.py
qh3/_compat.py
qh3/_hazmat.cpython-313t-s390x-linux-gnu.so
qh3/_hazmat.pyi
qh3/asyncio/__init__.py
qh3/asyncio/client.py
qh3/asyncio/protocol.py
qh3/asyncio/server.py
qh3/h3/__init__.py
qh3/h3/connection.py
qh3/h3/events.py
qh3/h3/exceptions.py
qh3/py.typed
qh3/quic/__init__.py
qh3/quic/configuration.py
qh3/quic/connection.py
qh3/quic/crypto.py
qh3/quic/events.py
qh3/quic/logger.py
qh3/quic/packet.py
qh3/quic/packet_builder.py
qh3/quic/recovery.py
qh3/quic/retry.py
qh3/quic/stream.py
qh3/tls.py
qh3-1.5.6.dist-info/RECORD
