Metadata-Version: 2.4
Name: qh3
Version: 1.5.6
Classifier: Development Status :: 5 - Production/Stable
Classifier: Environment :: Web Environment
Classifier: Intended Audience :: Developers
Classifier: License :: OSI Approved :: BSD License
Classifier: Operating System :: OS Independent
Classifier: Programming Language :: Python :: Implementation :: PyPy
Classifier: Programming Language :: Python :: Implementation :: CPython
Classifier: Programming Language :: Python
Classifier: Programming Language :: Python :: 3
Classifier: Programming Language :: Python :: 3.7
Classifier: Programming Language :: Python :: 3.8
Classifier: Programming Language :: Python :: 3.9
Classifier: Programming Language :: Python :: 3.10
Classifier: Programming Language :: Python :: 3.11
Classifier: Programming Language :: Python :: 3.12
Classifier: Programming Language :: Python :: 3.13
Classifier: Programming Language :: Python :: 3.14
Classifier: Topic :: Internet :: WWW/HTTP
License-File: LICENSE
Summary: A lightway and fast implementation of QUIC and HTTP/3
Home-Page: https://github.com/jawah/qh3
Author-email: Jeremy Lainé <jeremy.laine@m4x.org>
Maintainer-email: "Ahmed R. TAHRI" <tahri.ahmed@proton.me>
Requires-Python: >=3.7
Project-URL: homepage, https://github.com/jawah/qh3
Project-URL: documentation, https://qh3.readthedocs.io/
